fast_stoi-1.0.0.dist-info/METADATA
fast_stoi-1.0.0.dist-info/WHEEL
fast_stoi/__init__.py
fast_stoi/__pycache__/__init__.cpython-313.pyc
fast_stoi/fast_stoi.cpython-313-x86_64-linux-gnu.so
fast_stoi-1.0.0.dist-info/RECORD
