Metadata-Version: 2.4
Name: fast-stoi
Version: 1.0.0
Classifier: Programming Language :: Rust
Classifier: Programming Language :: Python :: Implementation :: CPython
Classifier: Programming Language :: Python :: Implementation :: PyPy
Requires-Dist: numpy>=1.24.4
Requires-Dist: torch>=2.5.1 ; extra == 'torch'
Provides-Extra: torch
Summary: Fast STOI implementation in Rust with Python bindings
Keywords: rust,stoi,audio
Author-email: Thibaut de Saivre <thibaut2saivre@gmail.com>
License-Expression: MIT OR Apache-2.0
Requires-Python: >=3.8
